Workbook

Sheet Overview
A1: Ledger — Launch Budget Overview
A2: Native iOS/Android ingredient-scanner app · all figures in USD · low/high ranges reflect scrappy-indie vs. well-resourced execution
A4: How to use this workbook
A5: Each tab below builds up one cost category with line-item assumptions (blue = editable inputs). This tab rolls every tab's subtotal into one picture. Edit hours, rates, or monthly spend on the detail tabs and everything here updates automatically.
A7: Category | B7: Detail tab | C7: One-time cost — Low | D7: One-time cost — High | E7: Monthly recurring — Low | F7: Monthly recurring — High
A8: Product development (build the app) | B8: Development | C8: =Development!G15 -> 16500 | D8: =Development!H15 -> 60250 | E8: 0 | F8: 0
A9: Ingredient database & content curation | B9: Data & Database | C9: ='Data & Database'!F10 -> 2960 | D9: ='Data & Database'!G10 -> 8960 | E9: ='Data & Database'!F16 -> 116.66667 | F9: ='Data & Database'!G16 -> 465
A10: Infrastructure, hosting & APIs | B10: Infrastructure & APIs | C10: 0 | D10: 0 | E10: ='Infrastructure & APIs'!C12 -> 1 | F10: ='Infrastructure & APIs'!D12 -> 232
A11: Legal, accounts & compliance | B11: Legal & Accounts | C11: ='Legal & Accounts'!B10 -> 1025 | D11: ='Legal & Accounts'!C10 -> 5725 | E11: ='Legal & Accounts'!B15 -> 8.25 | F11: ='Legal & Accounts'!C15 -> 8.25
A12: Marketing — pre-launch & launch | B12: Marketing | C12: =Marketing!B11 -> 3000 | D12: =Marketing!C11 -> 17300 | E12: 0 | F12: 0
A13: Marketing — ongoing (post-launch) | B13: Marketing | C13: 0 | D13: 0 | E13: =Marketing!B19 -> 800 | F13: =Marketing!C19 -> 8530
A14: TOTAL | C14: =SUM(C8:C13) -> 23485 | D14: =SUM(D8:D13) -> 92235 | E14: =SUM(E8:E13) -> 925.91667 | F14: =SUM(F8:F13) -> 9235.25
A16: Estimated Year-1 total (one-time + 12 months recurring) | C16: =C14+E14*12 -> 34596 | D16: =D14+F14*12 -> 203058 | E16: Low | F16: High
A18: Key takeaways
A19: • Development and the ~200-ingredient seed dataset (spec §7.C, §10) are the two big one-time costs — budget real hours for the content work, it's not just engineering.
A20: • Database itself stays cheap: the Ingredient table is tiny; the Product cache only gets expensive if you mirror all of Open Food Facts instead of caching on demand (spec §7.A) — see the Data & Database tab.
A21: • Marketing is the widest range in this budget — it scales with how aggressive the launch push is. The low end assumes organic/ASO + light paid; the high end assumes a real paid-UA budget.
A22: • Apple ($99/yr) and Google Play ($25 one-time) developer accounts should be opened early — spec §11 notes review time is outside your control.

Sheet Development
A1: Development Costs
A2: Roles are sized against the build order in spec §10 — a solo full-stack contractor can cover more than one row
A4: Role | B4: Approach / who does it | C4: Hours — Low | D4: Hours — High | E4: Rate/hr — Low | F4: Rate/hr — High | G4: Cost — Low | H4: Cost — High | I4: Notes (spec ref)
A5: React Native / Expo developer — core build | B5: Freelance contractor (Asia/HK-market rate); covers screens 1-4, scan flow, parsing/matching, compare screen | C5: 350 | D5: 600 | E5: 30 | F5: 60 | G5: =C5*E5 -> 10500 | H5: =D5*F5 -> 36000 | I5: Build order items 1, 3-7 (§10); Home/Scan/Label/Compare screens (§4)
A6: Backend / data engineer — Supabase & ETL | B6: Can be the same person as above if full-stack; Postgres schema, pg_trgm fuzzy matching, Open Food Facts ETL | C6: 80 | D6: 150 | E6: 35 | F6: 65 | G6: =C6*E6 -> 2800 | H6: =D6*F6 -> 9750 | I6: §6 schema, §7.C-D import pipeline, §8 tech stack
A7: UI/product designer — polish to production | B7: Freelance; turn the existing validated mockup (§5) into final assets, icons, empty/error states | C7: 40 | D7: 100 | E7: 35 | F7: 70 | G7: =C7*E7 -> 1400 | H7: =D7*F7 -> 7000 | I7: §5 design system already validated; §9 empty/error states
A8: QA / device testing | B8: Freelance or founder time; barcode/OCR edge cases, App Store review prep | C8: 40 | D8: 80 | E8: 25 | F8: 50 | G8: =C8*E8 -> 1000 | H8: =D8*F8 -> 4000 | I8: §9 non-negotiables; §11 review prep
A9: OCR/photo-fallback integration | B9: Wiring Google Vision API (or similar) for unbarcoded products | C9: 20 | D9: 45 | E9: 30 | F9: 60 | G9: =C9*E9 -> 600 | H9: =D9*F9 -> 2700 | I9: Build order item 6 (§10); §8 OCR notes
A10: Subtotal — engineering hours | C10: =SUM(C5:C9) -> 530 | D10: =SUM(D5:D9) -> 975 | G10: =SUM(G5:G9) -> 16300 | H10: =SUM(H5:H9) -> 59450
A12: One-off flat costs
A13: Expo EAS build & submit plan (annual) | G13: 0 | H13: 0 | I13: EAS free tier covers early internal builds; paid tier ($29-99/mo) only needed at higher build volume — see §11
A14: Dev devices for real-device testing (if needed) | G14: 200 | H14: 800 | I14: Barcode/OCR needs real hardware testing, not just simulator
A15: TOTAL — DEVELOPMENT (one-time) | G15: =G10+SUM(G13:G14) -> 16500 | H15: =H10+SUM(H13:H14) -> 60250

Sheet Data & Database
A1: Ingredient Database & Content Curation
A2: Build order items 1-2 (§10): this content work should run in parallel with screen-building, not after it
A4: One-time content build
A5: Task | B5: Hours — Low | C5: Hours — High | D5: Rate/hr — Low | E5: Rate/hr — High | F5: Cost — Low | G5: Cost — High | H5: Notes (spec ref)
A6: Curated ~200-ingredient core set: FDA lookup, CFR citation, plain-English explanation, human verification | B6: 100 | C6: 160 | D6: 25 | E6: 45 | F6: =B6*D6 -> 2500 | G6: =C6*E6 -> 7200 | H6: §7.C step 1 — 'budget real time for it, a spreadsheet verified entry-by-entry'
A7: Everyday allow-list curation (~40-60 items, salt/water/sugar/etc.) | B7: 4 | C7: 8 | D7: 20 | E7: 35 | F7: =B7*D7 -> 80 | G7: =C7*E7 -> 280 | H7: §3 'notable' definition, §6 everyday_allowlist field
A8: HK/Asia barcode coverage sample test (~50 barcodes vs. Open Food Facts) | B8: 4 | C8: 8 | D8: 20 | E8: 35 | F8: =B8*D8 -> 80 | G8: =C8*E8 -> 280 | H8: §7.A — decides whether manual-entry fallback is needed at launch, not v2
A9: Seed data import + ETL script (spreadsheet → Postgres) | B9: 10 | C9: 20 | D9: 30 | E9: 60 | F9: =B9*D9 -> 300 | G9: =C9*E9 -> 1200 | H9: §7.C step 2; overlaps with Development tab backend hours
A10: TOTAL — ONE-TIME CONTENT BUILD | F10: =SUM(F6:F9) -> 2960 | G10: =SUM(G6:G9) -> 8960
A12: Ongoing maintenance (recurring)
A13: Task | B13: Hours/quarter — Low | C13: Hours/quarter — High | D13: Rate/hr — Low | E13: Rate/hr — High | F13: Cost/mo — Low | G13: Cost/mo — High | H13: Notes
A14: Quarterly spot-check of core ~200 ingredients against FDA site (delistings, status changes) | B14: 8 | C14: 16 | D14: 25 | E14: 45 | F14: =(B14*D14)/3 -> 66.666667 | G14: =(C14*E14)/3 -> 240 | H14: §7.D — 'a manual review discipline, not an engineering problem'
A15: Backlog processing: new unmatched ingredients logged by the app | B15: 6 | C15: 15 | D15: 25 | E15: 45 | F15: =(B15*D15)/3 -> 50 | G15: =(C15*E15)/3 -> 225 | H15: §7.C step 5 — unmatched ingredients logged, not errored
A16: TOTAL — ONGOING MAINTENANCE (monthly) | F16: =SUM(F14:F15) -> 116.66667 | G16: =SUM(G14:G15) -> 465
A18: Database size — what actually needs storing
A19: Table / dataset | B19: Est. rows | C19: Est. size | D19: Notes
A20: Ingredient table (curated core + backlog) | B20: 200 → 2,000 | C20: < 10 MB | D20: Small by design — this is a reference table, not user data (§6)
A21: Product cache — barcode → ingredients, on-demand (recommended) | B21: 10k (yr 1) → 100k+ (growth) | C21: ~30 MB → ~400 MB | D21: Cache Open Food Facts hits as users scan, per §7.A live-API approach
A22: Full Open Food Facts bulk mirror (NOT recommended) | B22: 3,000,000+ | C22: Several GB+ | D22: Spec §7.A frames the bulk export as a seed/reference, not something to fully mirror — avoid unless you have a specific reason
A23: User accounts / scan history (only if added — not in v1 scope) | B23: — | C23: Small until scale | D23: §1-11 describe no accounts/personalization for v1; §13.2 flags this as a v2 idea

Sheet Infrastructure & APIs
A1: Infrastructure, Hosting & APIs
A2: All recurring — costs scale with usage, so two scenarios are shown (early/soft-launch vs. growth)
A4: Service | B4: What it's for | C4: Monthly — Low (early) | D4: Monthly — High (growth) | E4: Notes (spec ref)
A5: Supabase (Postgres + auth + storage) | B5: Backend hosting for Ingredient/Product tables, §6 schema | C5: 0 | D5: 100 | E5: Free tier (500MB DB) covers dev + soft launch; Pro tier ($25/mo base) needed once product cache grows — §11
A6: Google Vision API (OCR) | B6: Photo-fallback ingredient scanning, §8 | C6: 0 | D6: 60 | E6: ~1,000 units/mo free, then ~$1.50/1,000 units — scales with photo-scan volume
A7: Open Food Facts API | B7: Barcode → raw ingredient list, §7.A | C7: 0 | D7: 0 | E7: Free, ODbL-licensed
A8: USDA FoodData Central | B8: Secondary source for US-branded products, §7.A | C8: 0 | D8: 0 | E8: Free bulk CSV/JSON
A9: Domain name | B9: e.g. tryledger.app or similar | C9: 1 | D9: 2 | E9: $12-20/yr amortized monthly
A10: Error monitoring (e.g. Sentry) / analytics | B10: Crash reporting, usage analytics | C10: 0 | D10: 30 | E10: Generous free tiers exist at this scale
A11: Misc SaaS (design tools, project mgmt, email) | B11: Figma, Notion/Linear, transactional email, etc. | C11: 0 | D11: 40 | E11: Mostly avoidable pre-launch with free tiers
A12: TOTAL — INFRASTRUCTURE (monthly) | C12: =SUM(C5:C11) -> 1 | D12: =SUM(D5:D11) -> 232

Sheet Legal & Accounts
A1: Legal, Accounts & Compliance
A2: The legal framing in spec §1 (informational reference, not health advice) makes the ToS/disclaimer review worth doing properly
A4: One-time
A5: Item | B5: Cost — Low | C5: Cost — High | D5: Notes (spec ref)
A6: Google Play Console (one-time developer fee) | B6: 25 | C6: 25 | D6: §11 — required before Play Store submission
A7: Terms of Service / Privacy Policy + health-disclaimer legal review | B7: 800 | C7: 3000 | D7: §1 — 'informational reference tool, not a health-advice tool' is a legal positioning, worth a real review
A8: Business registration (sole proprietor / HK company) | B8: 200 | C8: 1200 | D8: Varies by structure — rough placeholder, confirm with a local accountant
A9: Trademark / name search (optional) | B9: 0 | C9: 1500 | D9: Optional but worth doing before committing to a brand name
A10: TOTAL — ONE-TIME | B10: =SUM(B6:B9) -> 1025 | C10: =SUM(C6:C9) -> 5725
A12: Recurring
A13: Item | B13: Cost/mo — Low | C13: Cost/mo — High | D13: Notes
A14: Apple Developer Program ($99/yr) | B14: =99/12 -> 8.25 | C14: =99/12 -> 8.25 | D14: §11 — required for App Store submission, enroll early (review can take days)
A15: TOTAL — RECURRING (monthly) | B15: =SUM(B14:B14) -> 8.25 | C15: =SUM(C14:C14) -> 8.25

Sheet Marketing
A1: Marketing — Pre-launch, Launch & Ongoing
A2: Widest range in the budget — scales directly with how aggressive the user-acquisition push is
A4: Pre-launch & launch (one-time)
A5: Item | B5: Cost — Low | C5: Cost — High | D5: Notes
A6: Landing page + email waitlist | B6: 0 | C6: 500 | D6: DIY page vs. designed/built by a freelancer
A7: Brand assets: App Store screenshots, preview video, icon refinement | B7: 500 | C7: 2500 | D7: Builds on the already-validated design system, §5
A8: ASO (App Store Optimization) keyword research/tools | B8: 0 | C8: 300 | D8: One-time research pass + tool subscription
A9: Launch PR (press kit + outreach, or a PR contractor) | B9: 1000 | C9: 6000 | D9: Positioning against Yuka (§12) is a genuine story for health/tech press
A10: Micro-influencer seeding (nutrition/health creators) | B10: 1500 | C10: 8000 | D10: Free product + flat fee for a launch batch of posts/reviews
A11: TOTAL — PRE-LAUNCH & LAUNCH | B11: =SUM(B6:B10) -> 3000 | C11: =SUM(C6:C10) -> 17300
A13: Ongoing (monthly, post-launch)
A14: Item | B14: Cost/mo — Low | C14: Cost/mo — High | D14: Notes
A15: Paid user acquisition (Apple Search Ads + Meta/Instagram) | B15: 500 | C15: 5000 | D15: At an est. $1-3 CPI for health apps, this buys roughly 200-3,000 installs/mo
A16: Content marketing (blog/SEO on food additives, social content) | B16: 300 | C16: 2000 | D16: DIY founder content vs. a freelance writer/creator
A17: Community & social management | B17: 0 | C17: 1500 | D17: Founder time (low) vs. part-time hire (high)
A18: Email/CRM tool for the waitlist and retention | B18: 0 | C18: 30 | D18: Free tiers cover early volume
A19: TOTAL — ONGOING (monthly) | B19: =SUM(B15:B18) -> 800 | C19: =SUM(C15:C18) -> 8530

Sheet Assumptions & Sources
A1: Assumptions & Sources
A2: Every figure in this workbook is an estimate — verify against current pricing before treating it as a real budget
A4: General
A5: • All figures are rough planning ranges based on general market rates as of 2026, not quotes — get real quotes from contractors/agencies before committing.
A6: • This budget is built directly from the product spec in ledger-product-spec.md (Ledger, native iOS/Android ingredient scanner) — every line item references the relevant section.
A7: • Freelance/contractor rates assume a Hong Kong/Asia-based hire, which is materially cheaper than US/EU agency rates; adjust the rate columns on the Development and Data & Database tabs if hiring elsewhere.
A8: • 'Low' scenarios generally assume a scrappy, mostly-solo build with free-tier infrastructure; 'High' scenarios assume more outside help and a real paid-marketing push.
A9: • Apple Developer Program and Google Play Console fees, and Supabase/Google Vision pricing tiers, are the figures most likely to drift — re-check these directly before finalizing a budget.
